shroud/__init__.py
shroud/aaa.py
shroud/ast.py
shroud/bbb.py
shroud/declast.py
shroud/generate.py
shroud/main.py
shroud/metadata.py
shroud/splicer.py
shroud/statements.py
shroud/todict.py
shroud/typemap.py
shroud/util.py
shroud/visitor.py
shroud/whelpers.py
shroud/wrapc.py
shroud/wrapf.py
shroud/wrapl.py
shroud/wrapp.py
llnl_shroud-0.13.0.dist-info/LICENSE
llnl_shroud-0.13.0.dist-info/METADATA
llnl_shroud-0.13.0.dist-info/NOTICE
llnl_shroud-0.13.0.dist-info/WHEEL
llnl_shroud-0.13.0.dist-info/entry_points.txt
llnl_shroud-0.13.0.dist-info/top_level.txt
llnl_shroud-0.13.0.dist-info/RECORD
