Metadata-Version: 2.1
Name: llnl-shroud
Version: 0.13.0
Summary: Generate Fortran and Python wrappers for C and C++ Libraries
Home-page: http://github.gov/llnl/shroud
Author: Lawrence Livermore National Laboratory
Author-email: shroud-users@groups.io
License: UNKNOWN
Download-URL: https://github.com/LLNL/shroud/archive/v0.13.0.tar.gz
Project-URL: Documentation, http://shroud.readthedocs.io/en/develop
Project-URL: Source, https://github.com/LLNL/shroud
Keywords: fortran development
Platform: UNKNOWN
Classifier: Development Status :: 4 - Beta
Classifier: Intended Audience :: Developers
Classifier: Topic :: Software Development :: Build Tools
Classifier: Topic :: Software Development :: Code Generators
Classifier: License :: OSI Approved :: BSD License
Classifier: Programming Language :: Python :: 2
Classifier: Programming Language :: Python :: 2.7
Classifier: Programming Language :: Python :: 3
Classifier: Programming Language :: Python :: 3.6
Classifier: Programming Language :: Python :: 3.7
Classifier: Programming Language :: Python :: 3.8
Classifier: Programming Language :: Python :: 3.9
Classifier: Programming Language :: Python :: 3.10
Requires-Dist: PyYAML (<=5.4.1,>=4.2b1)
